composable/__init__.py
composable/functions.py
composable_functions-0.0.0.dist-info/WHEEL
composable_functions-0.0.0.dist-info/METADATA
composable_functions-0.0.0.dist-info/RECORD
