Metadata-Version: 2.1
Name: composable-functions
Version: 0.0.0
Summary: Function composition in python
License: MIT
Keywords: functional,functional programming,fp,composition,function composition
Author: Francisco J. Jurado Moreno
Author-email: 9376816+Beetelbrox@users.noreply.github.com
Requires-Python: >=3.8,<4.0
Classifier: License :: OSI Approved :: MIT License
Classifier: Programming Language :: Python :: 3
Classifier: Programming Language :: Python :: 3.10
Classifier: Programming Language :: Python :: 3.8
Classifier: Programming Language :: Python :: 3.9
